README.rst
setup.py
typecorrector/__init__.py
typecorrector/corrector.py
typecorrector.egg-info/PKG-INFO
typecorrector.egg-info/SOURCES.txt
typecorrector.egg-info/dependency_links.txt
typecorrector.egg-info/pbr.json
typecorrector.egg-info/top_level.txt