Metadata-Version: 1.1
Name: typecorrector
Version: 0.2.1
Summary: A decorator meant to give type hints about function parameters as well as allow a margin of error
Home-page: https://github.com/fredgj/typecorrector
Author: Fredrik Gjertsen
Author-email: f.gjertsen@gmail.com
License: MIT
Keywords: types,type hints,type hinting
Platform: UNKNOWN
Classifier: Development Status :: 4 - Beta
Classifier: Intended Audience :: Developers
Classifier: License :: OSI Approved :: MIT License
Classifier: Operating System :: OS Independent
Classifier: Programming Language :: Python :: 2
Classifier: Programming Language :: Python :: 3
Classifier: Programming Language :: Python :: Implementation :: CPython
Classifier: Topic :: Utilities
